Workbook
Name Slicer_Category: #N/A
Name Slicer_Discount_Tier: #N/A
Name Slicer_Pack_Size: #N/A
Name Slicer_Price_Category: #N/A
Name Slicer_Stock_Status: #N/A
Name Zepto_data: ZeptoData[#All]

Sheet Raw Data
A1: Category | B1: name | C1: mrp | D1: discountPercent | E1: availableQuantity | F1: discountedSellingPrice | G1: weightInGms | H1: outOfStock | I1: quantity
A2: Fruits & Vegetables | B2: Onion | C2: 2500 | D2: 16 | E2: 3 | F2: 2100 | G2: 1000 | H2: FALSE | I2: 1
A3: Fruits & Vegetables | B3: Tomato Hybrid | C3: 4200 | D3: 16 | E3: 3 | F3: 3500 | G3: 1000 | H3: FALSE | I3: 1
A4: Fruits & Vegetables | B4: Tender Coconut | C4: 5100 | D4: 15 | E4: 3 | F4: 4300 | G4: 58 | H4: FALSE | I4: 1
A5: Fruits & Vegetables | B5: Coriander Leaves | C5: 2000 | D5: 15 | E5: 3 | F5: 1700 | G5: 100 | H5: FALSE | I5: 100
A6: Fruits & Vegetables | B6: Ladies Finger | C6: 1400 | D6: 14 | E6: 3 | F6: 1200 | G6: 250 | H6: FALSE | I6: 250
A7: Fruits & Vegetables | B7: Potato | C7: 3500 | D7: 17 | E7: 3 | F7: 2900 | G7: 1000 | H7: FALSE | I7: 1
A8: Fruits & Vegetables | B8: Lemon | C8: 7500 | D8: 16 | E8: 3 | F8: 6300 | G8: 200 | H8: FALSE | I8: 200
A9: Fruits & Vegetables | B9: Watermelon | C9: 5800 | D9: 15 | E9: 3 | F9: 4900 | G9: 58 | H9: FALSE | I9: 1
A10: Fruits & Vegetables | B10: Capsicum Green | C10: 2300 | D10: 17 | E10: 3 | F10: 1900 | G10: 250 | H10: FALSE | I10: 250
A11: Fruits & Vegetables | B11: Chilli Green | C11: 1900 | D11: 15 | E11: 3 | F11: 1600 | G11: 100 | H11: FALSE | I11: 100
A12: Fruits & Vegetables | B12: Banana Robusta | C12: 2900 | D12: 17 | E12: 3 | F12: 2400 | G12: 348 | H12: FALSE | I12: 6
A13: Fruits & Vegetables | B13: Garlic Indian | C13: 1100 | D13: 18 | E13: 3 | F13: 900 | G13: 100 | H13: FALSE | I13: 100
... A3733: Health & Hygiene | B3733: Dettol Antiseptic Liquid | C3733: 3000 | D3733: 0 | E3733: 0 | F3733: 3000 | G3733: 60 | H3733: TRUE | I3733: 60

Sheet Analysis
A3: Row Labels | B3: Count of name | C3: Average of discountPercent
A4: Health & Hygiene | B4: 97 | C4: 8.0515464
A5: Grand Total | B5: 97 | C5: 8.0515464
A23: Count of name | B23: Column Labels | F23: Row Labels | G23: Count of name | O23: Row Labels | P23: Average of discountPercent
A24: Row Labels | B24: FALSE | C24: TRUE | D24: Grand Total | F24: Health & Hygiene | G24: 97 | O24: Health & Hygiene | P24: 8.0515464
A25: Health & Hygiene | B25: 0.86597938 | C25: 0.13402062 | D25: 1 | F25: Grand Total | G25: 97 | O25: Grand Total | P25: 8.0515464
A26: Grand Total | B26: 0.86597938 | C26: 0.13402062 | D26: 1
O42: Row Labels | P42: Count of Name2
A43: Sum of Sale_Price | B43: Average of Sale_Price2 | C43: Count of Name2 | O43: Budget | P43: 21
A44: 14148 | B44: 145.85567 | C44: 97 | E44: =GETPIVOTDATA("Sum of Sale_Price",$A$43) -> 14148 | F44: =GETPIVOTDATA("Average of Sale_Price2",$A$43) -> 145.85567 | G44: =GETPIVOTDATA("Count of Name2",$A$43) -> 97 | K44: Row Labels | L44: Count of Name2 | O44: Mid-Range | P44: 39
K45: HEALTHY | L45: 73 | O45: Premium | P45: 37
K46: LOW STOCK | L46: 11 | O46: Grand Total | P46: 97
K47: Out of Stock | L47: 13
K48: Grand Total | L48: 97

Sheet DASHBOARD

Sheet Cleaned Data
A1: Category | B1: name | C1: Name2 | D1: mrp | E1: MRP_Rupees | F1: discountPercent | G1: availableQuantity | H1: discountedSellingPrice | I1: Sale_Price | J1: weightInGms | K1: outOfStock | L1: quantity | M1: Blank | N1: Savings | O1: Stock_Status | P1: Price_Category | Q1: Is_Discount_Correct? | R1: Discount_Tier | S1: Pack_Size
A2: Fruits & Vegetables | B2: Onion | C2: =TRIM(ZeptoData[[#This Row],[name]]) -> Onion | D2: 2500 | E2: ='Cleaned Data'!F5 -> 15 | F2: 16 | G2: 3 | H2: 2100 | I2: =ZeptoData[[#This Row],[discountedSellingPrice]]/100 -> 21 | J2: 1000 | K2: FALSE | L2: 1 | N2: =ZeptoData[[#This Row],[MRP_Rupees]] - ZeptoData[[#This Row],[Sale_Price]] -> -6 | O2: =IF(ZeptoData[[#This Row],[outOfStock]]=TRUE, "Out of Stock", IF(ZeptoData[[#This Row],[availableQuantity]]<=2, "LOW STOCK", "HEALTHY")) -> HEALTHY | P2: {=_xlfn.IFS(ZeptoData[[#This Row],[Sale_Price]]<50, "Budget", ZeptoData[[#This Row],[Sale_Price]]<150, "Mid-Range", ZeptoData[[#This Row],[Sale_Price]]>=150, "Premium")} -> Budget | Q2: =IF(ROUND(((ZeptoData[[#This Row],[mrp]]-ZeptoData[[#This Row],[discountedSellingPrice]])/ZeptoData[[#This Row],[mrp]])*100,0) = ZeptoData[[#This Row],[discountPercent]], "Match", "Error") -> Match | R2: {=_xlfn.IFS(ZeptoData[[#This Row],[discountPercent]]=0, "No Discount", ZeptoData[[#This Row],[discountPercent]]<=15, "Standard (1-15%)", ZeptoData[[#This Row],[discountPercent]]>15, "Mega (>15%)")} -> Mega (>15%) | S2: {=_xlfn.IFS(ZeptoData[[#This Row],[weightInGms]]<=100, "Small (<100g)", ZeptoData[[#This Row],[weightInGms]]<=500, "Medium (100-500g)", ZeptoData[[#This Row],[weightInGms]]>500, "Large (>500g)")} -> Large (>500g)
A3: Fruits & Vegetables | B3: Tomato Hybrid | C3: =TRIM(ZeptoData[[#This Row],[name]]) -> Tomato Hybrid | D3: 4200 | E3: ='Cleaned Data'!F6 -> 14 | F3: 16 | G3: 3 | H3: 3500 | I3: =ZeptoData[[#This Row],[discountedSellingPrice]]/100 -> 35 | J3: 1000 | K3: FALSE | L3: 1 | N3: =ZeptoData[[#This Row],[MRP_Rupees]] - ZeptoData[[#This Row],[Sale_Price]] -> -21 | O3: =IF(ZeptoData[[#This Row],[outOfStock]]=TRUE, "Out of Stock", IF(ZeptoData[[#This Row],[availableQuantity]]<=2, "LOW STOCK", "HEALTHY")) -> HEALTHY | P3: {=_xlfn.IFS(ZeptoData[[#This Row],[Sale_Price]]<50, "Budget", ZeptoData[[#This Row],[Sale_Price]]<150, "Mid-Range", ZeptoData[[#This Row],[Sale_Price]]>=150, "Premium")} -> Budget | Q3: =IF(ROUND(((ZeptoData[[#This Row],[mrp]]-ZeptoData[[#This Row],[discountedSellingPrice]])/ZeptoData[[#This Row],[mrp]])*100,0) = ZeptoData[[#This Row],[discountPercent]], "Match", "Error") -> Error | R3: {=_xlfn.IFS(ZeptoData[[#This Row],[discountPercent]]=0, "No Discount", ZeptoData[[#This Row],[discountPercent]]<=15, "Standard (1-15%)", ZeptoData[[#This Row],[discountPercent]]>15, "Mega (>15%)")} -> Mega (>15%) | S3: {=_xlfn.IFS(ZeptoData[[#This Row],[weightInGms]]<=100, "Small (<100g)", ZeptoData[[#This Row],[weightInGms]]<=500, "Medium (100-500g)", ZeptoData[[#This Row],[weightInGms]]>500, "Large (>500g)")} -> Large (>500g)
A4: Fruits & Vegetables | B4: Tender Coconut | C4: =TRIM(ZeptoData[[#This Row],[name]]) -> Tender Coconut | D4: 5100 | E4: ='Cleaned Data'!F7 -> 17 | F4: 15 | G4: 3 | H4: 4300 | I4: =ZeptoData[[#This Row],[discountedSellingPrice]]/100 -> 43 | J4: 58 | K4: FALSE | L4: 1 | N4: =ZeptoData[[#This Row],[MRP_Rupees]] - ZeptoData[[#This Row],[Sale_Price]] -> -26 | O4: =IF(ZeptoData[[#This Row],[outOfStock]]=TRUE, "Out of Stock", IF(ZeptoData[[#This Row],[availableQuantity]]<=2, "LOW STOCK", "HEALTHY")) -> HEALTHY | P4: {=_xlfn.IFS(ZeptoData[[#This Row],[Sale_Price]]<50, "Budget", ZeptoData[[#This Row],[Sale_Price]]<150, "Mid-Range", ZeptoData[[#This Row],[Sale_Price]]>=150, "Premium")} -> Budget | Q4: =IF(ROUND(((ZeptoData[[#This Row],[mrp]]-ZeptoData[[#This Row],[discountedSellingPrice]])/ZeptoData[[#This Row],[mrp]])*100,0) = ZeptoData[[#This Row],[discountPercent]], "Match", "Error") -> Error | R4: {=_xlfn.IFS(ZeptoData[[#This Row],[discountPercent]]=0, "No Discount", ZeptoData[[#This Row],[discountPercent]]<=15, "Standard (1-15%)", ZeptoData[[#This Row],[discountPercent]]>15, "Mega (>15%)")} -> Standard (1-15%) | S4: {=_xlfn.IFS(ZeptoData[[#This Row],[weightInGms]]<=100, "Small (<100g)", ZeptoData[[#This Row],[weightInGms]]<=500, "Medium (100-500g)", ZeptoData[[#This Row],[weightInGms]]>500, "Large (>500g)")} -> Small (<100g)
A5: Fruits & Vegetables | B5: Coriander Leaves | C5: =TRIM(ZeptoData[[#This Row],[name]]) -> Coriander Leaves | D5: 2000 | E5: ='Cleaned Data'!F8 -> 16 | F5: 15 | G5: 3 | H5: 1700 | I5: =ZeptoData[[#This Row],[discountedSellingPrice]]/100 -> 17 | J5: 100 | K5: FALSE | L5: 100 | N5: =ZeptoData[[#This Row],[MRP_Rupees]] - ZeptoData[[#This Row],[Sale_Price]] -> -1 | O5: =IF(ZeptoData[[#This Row],[outOfStock]]=TRUE, "Out of Stock", IF(ZeptoData[[#This Row],[availableQuantity]]<=2, "LOW STOCK", "HEALTHY")) -> HEALTHY | P5: {=_xlfn.IFS(ZeptoData[[#This Row],[Sale_Price]]<50, "Budget", ZeptoData[[#This Row],[Sale_Price]]<150, "Mid-Range", ZeptoData[[#This Row],[Sale_Price]]>=150, "Premium")} -> Budget | Q5: =IF(ROUND(((ZeptoData[[#This Row],[mrp]]-ZeptoData[[#This Row],[discountedSellingPrice]])/ZeptoData[[#This Row],[mrp]])*100,0) = ZeptoData[[#This Row],[discountPercent]], "Match", "Error") -> Match | R5: {=_xlfn.IFS(ZeptoData[[#This Row],[discountPercent]]=0, "No Discount", ZeptoData[[#This Row],[discountPercent]]<=15, "Standard (1-15%)", ZeptoData[[#This Row],[discountPercent]]>15, "Mega (>15%)")} -> Standard (1-15%) | S5: {=_xlfn.IFS(ZeptoData[[#This Row],[weightInGms]]<=100, "Small (<100g)", ZeptoData[[#This Row],[weightInGms]]<=500, "Medium (100-500g)", ZeptoData[[#This Row],[weightInGms]]>500, "Large (>500g)")} -> Small (<100g)
A6: Fruits & Vegetables | B6: Ladies Finger | C6: =TRIM(ZeptoData[[#This Row],[name]]) -> Ladies Finger | D6: 1400 | E6: ='Cleaned Data'!F9 -> 15 | F6: 14 | G6: 3 | H6: 1200 | I6: =ZeptoData[[#This Row],[discountedSellingPrice]]/100 -> 12 | J6: 250 | K6: FALSE | L6: 250 | N6: =ZeptoData[[#This Row],[MRP_Rupees]] - ZeptoData[[#This Row],[Sale_Price]] -> 3 | O6: =IF(ZeptoData[[#This Row],[outOfStock]]=TRUE, "Out of Stock", IF(ZeptoData[[#This Row],[availableQuantity]]<=2, "LOW STOCK", "HEALTHY")) -> HEALTHY | P6: {=_xlfn.IFS(ZeptoData[[#This Row],[Sale_Price]]<50, "Budget", ZeptoData[[#This Row],[Sale_Price]]<150, "Mid-Range", ZeptoData[[#This Row],[Sale_Price]]>=150, "Premium")} -> Budget | Q6: =IF(ROUND(((ZeptoData[[#This Row],[mrp]]-ZeptoData[[#This Row],[discountedSellingPrice]])/ZeptoData[[#This Row],[mrp]])*100,0) = ZeptoData[[#This Row],[discountPercent]], "Match", "Error") -> Match | R6: {=_xlfn.IFS(ZeptoData[[#This Row],[discountPercent]]=0, "No Discount", ZeptoData[[#This Row],[discountPercent]]<=15, "Standard (1-15%)", ZeptoData[[#This Row],[discountPercent]]>15, "Mega (>15%)")} -> Standard (1-15%) | S6: {=_xlfn.IFS(ZeptoData[[#This Row],[weightInGms]]<=100, "Small (<100g)", ZeptoData[[#This Row],[weightInGms]]<=500, "Medium (100-500g)", ZeptoData[[#This Row],[weightInGms]]>500, "Large (>500g)")} -> Medium (100-500g)
A7: Fruits & Vegetables | B7: Potato | C7: =TRIM(ZeptoData[[#This Row],[name]]) -> Potato | D7: 3500 | E7: ='Cleaned Data'!F10 -> 17 | F7: 17 | G7: 3 | H7: 2900 | I7: =ZeptoData[[#This Row],[discountedSellingPrice]]/100 -> 29 | J7: 1000 | K7: FALSE | L7: 1 | N7: =ZeptoData[[#This Row],[MRP_Rupees]] - ZeptoData[[#This Row],[Sale_Price]] -> -12 | O7: =IF(ZeptoData[[#This Row],[outOfStock]]=TRUE, "Out of Stock", IF(ZeptoData[[#This Row],[availableQuantity]]<=2, "LOW STOCK", "HEALTHY")) -> HEALTHY | P7: {=_xlfn.IFS(ZeptoData[[#This Row],[Sale_Price]]<50, "Budget", ZeptoData[[#This Row],[Sale_Price]]<150, "Mid-Range", ZeptoData[[#This Row],[Sale_Price]]>=150, "Premium")} -> Budget | Q7: =IF(ROUND(((ZeptoData[[#This Row],[mrp]]-ZeptoData[[#This Row],[discountedSellingPrice]])/ZeptoData[[#This Row],[mrp]])*100,0) = ZeptoData[[#This Row],[discountPercent]], "Match", "Error") -> Match | R7: {=_xlfn.IFS(ZeptoData[[#This Row],[discountPercent]]=0, "No Discount", ZeptoData[[#This Row],[discountPercent]]<=15, "Standard (1-15%)", ZeptoData[[#This Row],[discountPercent]]>15, "Mega (>15%)")} -> Mega (>15%) | S7: {=_xlfn.IFS(ZeptoData[[#This Row],[weightInGms]]<=100, "Small (<100g)", ZeptoData[[#This Row],[weightInGms]]<=500, "Medium (100-500g)", ZeptoData[[#This Row],[weightInGms]]>500, "Large (>500g)")} -> Large (>500g)
A8: Fruits & Vegetables | B8: Lemon | C8: =TRIM(ZeptoData[[#This Row],[name]]) -> Lemon | D8: 7500 | E8: ='Cleaned Data'!F11 -> 15 | F8: 16 | G8: 3 | H8: 6300 | I8: =ZeptoData[[#This Row],[discountedSellingPrice]]/100 -> 63 | J8: 200 | K8: FALSE | L8: 200 | N8: =ZeptoData[[#This Row],[MRP_Rupees]] - ZeptoData[[#This Row],[Sale_Price]] -> -48 | O8: =IF(ZeptoData[[#This Row],[outOfStock]]=TRUE, "Out of Stock", IF(ZeptoData[[#This Row],[availableQuantity]]<=2, "LOW STOCK", "HEALTHY")) -> HEALTHY | P8: {=_xlfn.IFS(ZeptoData[[#This Row],[Sale_Price]]<50, "Budget", ZeptoData[[#This Row],[Sale_Price]]<150, "Mid-Range", ZeptoData[[#This Row],[Sale_Price]]>=150, "Premium")} -> Mid-Range | Q8: =IF(ROUND(((ZeptoData[[#This Row],[mrp]]-ZeptoData[[#This Row],[discountedSellingPrice]])/ZeptoData[[#This Row],[mrp]])*100,0) = ZeptoData[[#This Row],[discountPercent]], "Match", "Error") -> Match | R8: {=_xlfn.IFS(ZeptoData[[#This Row],[discountPercent]]=0, "No Discount", ZeptoData[[#This Row],[discountPercent]]<=15, "Standard (1-15%)", ZeptoData[[#This Row],[discountPercent]]>15, "Mega (>15%)")} -> Mega (>15%) | S8: {=_xlfn.IFS(ZeptoData[[#This Row],[weightInGms]]<=100, "Small (<100g)", ZeptoData[[#This Row],[weightInGms]]<=500, "Medium (100-500g)", ZeptoData[[#This Row],[weightInGms]]>500, "Large (>500g)")} -> Medium (100-500g)
A9: Fruits & Vegetables | B9: Watermelon | C9: =TRIM(ZeptoData[[#This Row],[name]]) -> Watermelon | D9: 5800 | E9: ='Cleaned Data'!F12 -> 17 | F9: 15 | G9: 3 | H9: 4900 | I9: =ZeptoData[[#This Row],[discountedSellingPrice]]/100 -> 49 | J9: 58 | K9: FALSE | L9: 1 | N9: =ZeptoData[[#This Row],[MRP_Rupees]] - ZeptoData[[#This Row],[Sale_Price]] -> -32 | O9: =IF(ZeptoData[[#This Row],[outOfStock]]=TRUE, "Out of Stock", IF(ZeptoData[[#This Row],[availableQuantity]]<=2, "LOW STOCK", "HEALTHY")) -> HEALTHY | P9: {=_xlfn.IFS(ZeptoData[[#This Row],[Sale_Price]]<50, "Budget", ZeptoData[[#This Row],[Sale_Price]]<150, "Mid-Range", ZeptoData[[#This Row],[Sale_Price]]>=150, "Premium")} -> Budget | Q9: =IF(ROUND(((ZeptoData[[#This Row],[mrp]]-ZeptoData[[#This Row],[discountedSellingPrice]])/ZeptoData[[#This Row],[mrp]])*100,0) = ZeptoData[[#This Row],[discountPercent]], "Match", "Error") -> Error | R9: {=_xlfn.IFS(ZeptoData[[#This Row],[discountPercent]]=0, "No Discount", ZeptoData[[#This Row],[discountPercent]]<=15, "Standard (1-15%)", ZeptoData[[#This Row],[discountPercent]]>15, "Mega (>15%)")} -> Standard (1-15%) | S9: {=_xlfn.IFS(ZeptoData[[#This Row],[weightInGms]]<=100, "Small (<100g)", ZeptoData[[#This Row],[weightInGms]]<=500, "Medium (100-500g)", ZeptoData[[#This Row],[weightInGms]]>500, "Large (>500g)")} -> Small (<100g)
A10: Fruits & Vegetables | B10: Capsicum Green | C10: =TRIM(ZeptoData[[#This Row],[name]]) -> Capsicum Green | D10: 2300 | E10: ='Cleaned Data'!F13 -> 18 | F10: 17 | G10: 3 | H10: 1900 | I10: =ZeptoData[[#This Row],[discountedSellingPrice]]/100 -> 19 | J10: 250 | K10: FALSE | L10: 250 | N10: =ZeptoData[[#This Row],[MRP_Rupees]] - ZeptoData[[#This Row],[Sale_Price]] -> -1 | O10: =IF(ZeptoData[[#This Row],[outOfStock]]=TRUE, "Out of Stock", IF(ZeptoData[[#This Row],[availableQuantity]]<=2, "LOW STOCK", "HEALTHY")) -> HEALTHY | P10: {=_xlfn.IFS(ZeptoData[[#This Row],[Sale_Price]]<50, "Budget", ZeptoData[[#This Row],[Sale_Price]]<150, "Mid-Range", ZeptoData[[#This Row],[Sale_Price]]>=150, "Premium")} -> Budget | Q10: =IF(ROUND(((ZeptoData[[#This Row],[mrp]]-ZeptoData[[#This Row],[discountedSellingPrice]])/ZeptoData[[#This Row],[mrp]])*100,0) = ZeptoData[[#This Row],[discountPercent]], "Match", "Error") -> Match | R10: {=_xlfn.IFS(ZeptoData[[#This Row],[discountPercent]]=0, "No Discount", ZeptoData[[#This Row],[discountPercent]]<=15, "Standard (1-15%)", ZeptoData[[#This Row],[discountPercent]]>15, "Mega (>15%)")} -> Mega (>15%) | S10: {=_xlfn.IFS(ZeptoData[[#This Row],[weightInGms]]<=100, "Small (<100g)", ZeptoData[[#This Row],[weightInGms]]<=500, "Medium (100-500g)", ZeptoData[[#This Row],[weightInGms]]>500, "Large (>500g)")} -> Medium (100-500g)
A11: Fruits & Vegetables | B11: Chilli Green | C11: =TRIM(ZeptoData[[#This Row],[name]]) -> Chilli Green | D11: 1900 | E11: ='Cleaned Data'!F14 -> 15 | F11: 15 | G11: 3 | H11: 1600 | I11: =ZeptoData[[#This Row],[discountedSellingPrice]]/100 -> 16 | J11: 100 | K11: FALSE | L11: 100 | N11: =ZeptoData[[#This Row],[MRP_Rupees]] - ZeptoData[[#This Row],[Sale_Price]] -> -1 | O11: =IF(ZeptoData[[#This Row],[outOfStock]]=TRUE, "Out of Stock", IF(ZeptoData[[#This Row],[availableQuantity]]<=2, "LOW STOCK", "HEALTHY")) -> HEALTHY | P11: {=_xlfn.IFS(ZeptoData[[#This Row],[Sale_Price]]<50, "Budget", ZeptoData[[#This Row],[Sale_Price]]<150, "Mid-Range", ZeptoData[[#This Row],[Sale_Price]]>=150, "Premium")} -> Budget | Q11: =IF(ROUND(((ZeptoData[[#This Row],[mrp]]-ZeptoData[[#This Row],[discountedSellingPrice]])/ZeptoData[[#This Row],[mrp]])*100,0) = ZeptoData[[#This Row],[discountPercent]], "Match", "Error") -> Error | R11: {=_xlfn.IFS(ZeptoData[[#This Row],[discountPercent]]=0, "No Discount", ZeptoData[[#This Row],[discountPercent]]<=15, "Standard (1-15%)", ZeptoData[[#This Row],[discountPercent]]>15, "Mega (>15%)")} -> Standard (1-15%) | S11: {=_xlfn.IFS(ZeptoData[[#This Row],[weightInGms]]<=100, "Small (<100g)", ZeptoData[[#This Row],[weightInGms]]<=500, "Medium (100-500g)", ZeptoData[[#This Row],[weightInGms]]>500, "Large (>500g)")} -> Small (<100g)
A12: Fruits & Vegetables | B12: Banana Robusta | C12: =TRIM(ZeptoData[[#This Row],[name]]) -> Banana Robusta | D12: 2900 | E12: ='Cleaned Data'!F15 -> 14 | F12: 17 | G12: 3 | H12: 2400 | I12: =ZeptoData[[#This Row],[discountedSellingPrice]]/100 -> 24 | J12: 348 | K12: FALSE | L12: 6 | N12: =ZeptoData[[#This Row],[MRP_Rupees]] - ZeptoData[[#This Row],[Sale_Price]] -> -10 | O12: =IF(ZeptoData[[#This Row],[outOfStock]]=TRUE, "Out of Stock", IF(ZeptoData[[#This Row],[availableQuantity]]<=2, "LOW STOCK", "HEALTHY")) -> HEALTHY | P12: {=_xlfn.IFS(ZeptoData[[#This Row],[Sale_Price]]<50, "Budget", ZeptoData[[#This Row],[Sale_Price]]<150, "Mid-Range", ZeptoData[[#This Row],[Sale_Price]]>=150, "Premium")} -> Budget | Q12: =IF(ROUND(((ZeptoData[[#This Row],[mrp]]-ZeptoData[[#This Row],[discountedSellingPrice]])/ZeptoData[[#This Row],[mrp]])*100,0) = ZeptoData[[#This Row],[discountPercent]], "Match", "Error") -> Match | R12: {=_xlfn.IFS(ZeptoData[[#This Row],[discountPercent]]=0, "No Discount", ZeptoData[[#This Row],[discountPercent]]<=15, "Standard (1-15%)", ZeptoData[[#This Row],[discountPercent]]>15, "Mega (>15%)")} -> Mega (>15%) | S12: {=_xlfn.IFS(ZeptoData[[#This Row],[weightInGms]]<=100, "Small (<100g)", ZeptoData[[#This Row],[weightInGms]]<=500, "Medium (100-500g)", ZeptoData[[#This Row],[weightInGms]]>500, "Large (>500g)")} -> Medium (100-500g)
A13: Fruits & Vegetables | B13: Garlic Indian | C13: =TRIM(ZeptoData[[#This Row],[name]]) -> Garlic Indian | D13: 1100 | E13: ='Cleaned Data'!F16 -> 15 | F13: 18 | G13: 3 | H13: 900 | I13: =ZeptoData[[#This Row],[discountedSellingPrice]]/100 -> 9 | J13: 100 | K13: FALSE | L13: 100 | N13: =ZeptoData[[#This Row],[MRP_Rupees]] - ZeptoData[[#This Row],[Sale_Price]] -> 6 | O13: =IF(ZeptoData[[#This Row],[outOfStock]]=TRUE, "Out of Stock", IF(ZeptoData[[#This Row],[availableQuantity]]<=2, "LOW STOCK", "HEALTHY")) -> HEALTHY | P13: {=_xlfn.IFS(ZeptoData[[#This Row],[Sale_Price]]<50, "Budget", ZeptoData[[#This Row],[Sale_Price]]<150, "Mid-Range", ZeptoData[[#This Row],[Sale_Price]]>=150, "Premium")} -> Budget | Q13: =IF(ROUND(((ZeptoData[[#This Row],[mrp]]-ZeptoData[[#This Row],[discountedSellingPrice]])/ZeptoData[[#This Row],[mrp]])*100,0) = ZeptoData[[#This Row],[discountPercent]], "Match", "Error") -> Match | R13: {=_xlfn.IFS(ZeptoData[[#This Row],[discountPercent]]=0, "No Discount", ZeptoData[[#This Row],[discountPercent]]<=15, "Standard (1-15%)", ZeptoData[[#This Row],[discountPercent]]>15, "Mega (>15%)")} -> Mega (>15%) | S13: {=_xlfn.IFS(ZeptoData[[#This Row],[weightInGms]]<=100, "Small (<100g)", ZeptoData[[#This Row],[weightInGms]]<=500, "Medium (100-500g)", ZeptoData[[#This Row],[weightInGms]]>500, "Large (>500g)")} -> Small (<100g)
... A3730: Health & Hygiene | B3730: Dettol Antiseptic Liquid | C3730: =TRIM(ZeptoData[[#This Row],[name]]) -> Dettol Antiseptic Liquid | D3730: 3000 | E3730: ='Cleaned Data'!F3733 -> 0 | F3730: 0 | G3730: 0 | H3730: 3000 | I3730: =ZeptoData[[#This Row],[discountedSellingPrice]]/100 -> 30 | J3730: 60 | K3730: TRUE | L3730: 60 | N3730: =ZeptoData[[#This Row],[MRP_Rupees]] - ZeptoData[[#This Row],[Sale_Price]] -> -30 | O3730: =IF(ZeptoData[[#This Row],[outOfStock]]=TRUE, "Out of Stock", IF(ZeptoData[[#This Row],[availableQuantity]]<=2, "LOW STOCK", "HEALTHY")) -> Out of Stock | P3730: {=_xlfn.IFS(ZeptoData[[#This Row],[Sale_Price]]<50, "Budget", ZeptoData[[#This Row],[Sale_Price]]<150, "Mid-Range", ZeptoData[[#This Row],[Sale_Price]]>=150, "Premium")} -> Budget | Q3730: =IF(ROUND(((ZeptoData[[#This Row],[mrp]]-ZeptoData[[#This Row],[discountedSellingPrice]])/ZeptoData[[#This Row],[mrp]])*100,0) = ZeptoData[[#This Row],[discountPercent]], "Match", "Error") -> Match | R3730: {=_xlfn.IFS(ZeptoData[[#This Row],[discountPercent]]=0, "No Discount", ZeptoData[[#This Row],[discountPercent]]<=15, "Standard (1-15%)", ZeptoData[[#This Row],[discountPercent]]>15, "Mega (>15%)")} -> No Discount | S3730: {=_xlfn.IFS(ZeptoData[[#This Row],[weightInGms]]<=100, "Small (<100g)", ZeptoData[[#This Row],[weightInGms]]<=500, "Medium (100-500g)", ZeptoData[[#This Row],[weightInGms]]>500, "Large (>500g)")} -> Small (<100g)
